mango_library-1.1.0-py3.8-nspkg.pth
mango_library/coalition/__init__.py
mango_library/coalition/core.py
mango_library/negotiation/__init__.py
mango_library/negotiation/termination.py
mango_library/negotiation/util.py
mango_library/negotiation/cohda/__init__.py
mango_library/negotiation/cohda/cohda_messages.py
mango_library/negotiation/cohda/cohda_negotiation.py
mango_library/negotiation/cohda/cohda_solution_aggregation.py
mango_library/negotiation/cohda/cohda_starting.py
mango_library/negotiation/cohda/data_classes.py
mango_library/negotiation/multiobjective_cohda/__init__.py
mango_library/negotiation/multiobjective_cohda/cohda_messages.py
mango_library/negotiation/multiobjective_cohda/data_classes.py
mango_library/negotiation/multiobjective_cohda/mocohda_solution_aggregation.py
mango_library/negotiation/multiobjective_cohda/mocohda_starting.py
mango_library/negotiation/multiobjective_cohda/multiobjective_cohda.py
mango_library-1.1.0.dist-info/LICENSE
mango_library-1.1.0.dist-info/METADATA
mango_library-1.1.0.dist-info/WHEEL
mango_library-1.1.0.dist-info/namespace_packages.txt
mango_library-1.1.0.dist-info/top_level.txt
mango_library-1.1.0.dist-info/RECORD
