Metadata-Version: 2.1
Name: mango-library
Version: 1.1.0
Summary: Library for the Modular Python Agent Framework MANGO
Author: Mango Team
Author-email: mango@offis.de
License: MIT
Classifier: License :: OSI Approved :: MIT License
Classifier: Programming Language :: Python
Classifier: Programming Language :: Python :: 3
Classifier: Programming Language :: Python :: 3.7
Classifier: Programming Language :: Python :: Implementation :: CPython
Classifier: Programming Language :: Python :: Implementation :: PyPy
Requires-Python: >=3.7.0
License-File: LICENSE
Requires-Dist: numpy
Requires-Dist: mango-agents ==1.0.0
